setup.py
pyedsl/__init__.py
pyedsl/info.py
pyedsl/pd_impl.py
pyedsl/xml_impl.py
pyedsl.egg-info/PKG-INFO
pyedsl.egg-info/SOURCES.txt
pyedsl.egg-info/dependency_links.txt
pyedsl.egg-info/entry_points.txt
pyedsl.egg-info/top_level.txt
pyedsl.egg-info/zip-safe