Metadata-Version: 1.0
Name: pyedsl
Version: 0.1.27
Summary: pyedsl v. 0.1.27
